MANIFEST.in
README.md
setup.cfg
setup.py
versioneer.py
csirtg_ipsml_tf/__init__.py
csirtg_ipsml_tf/_version.py
csirtg_ipsml_tf/constants.py
csirtg_ipsml_tf/features.py
csirtg_ipsml_tf/geo.py
csirtg_ipsml_tf/train.py
csirtg_ipsml_tf/utils.py
csirtg_ipsml_tf.egg-info/PKG-INFO
csirtg_ipsml_tf.egg-info/SOURCES.txt
csirtg_ipsml_tf.egg-info/dependency_links.txt
csirtg_ipsml_tf.egg-info/entry_points.txt
csirtg_ipsml_tf.egg-info/requires.txt
csirtg_ipsml_tf.egg-info/top_level.txt
data/cc.txt
data/model.h5
data/timezones.txt
data/weights.h5
test/__init__.py
test/test_basics.py