Metadata-Version: 1.0
Name: csirtg-ipsml-tf
Version: 0.0a10
Summary: CSIRTG IP ML Framework - TensorFlow
Home-page: https://github.com/csirtgadgets/csirtg-ipsml-tf-py
Author: Wes Young
Author-email: wes@csirtgadgets.com
License: MPLv2
Keywords: network,security
Platform: UNKNOWN
